{
  "url": "https://redis.io/downloads/",
  "runs": 3,
  "performance": 32,
  "accessibility": 89,
  "bestPractices": 74,
  "seo": 100,
  "timestamp": "2025-08-01T08:47:48.569Z",
  "rawResults": [
    {
      "performance": 33,
      "accessibility": 89,
      "bestPractices": 74,
      "seo": 100,
      "timestamp": "2025-08-01T08:45:40.251Z"
    },
    {
      "performance": 32,
      "accessibility": 89,
      "bestPractices": 74,
      "seo": 100,
      "timestamp": "2025-08-01T08:46:44.379Z"
    },
    {
      "performance": 32,
      "accessibility": 89,
      "bestPractices": 74,
      "seo": 100,
      "timestamp": "2025-08-01T08:47:48.569Z"
    }
  ]
}