{
  "url": "https://redis.io/software/",
  "runs": 3,
  "performance": 35,
  "accessibility": 100,
  "bestPractices": 56,
  "seo": 86,
  "timestamp": "2026-05-11T11:14:59.795Z",
  "rawResults": [
    {
      "performance": 34,
      "accessibility": 100,
      "bestPractices": 56,
      "seo": 86,
      "timestamp": "2026-05-11T11:12:44.558Z"
    },
    {
      "performance": 36,
      "accessibility": 100,
      "bestPractices": 56,
      "seo": 86,
      "timestamp": "2026-05-11T11:13:52.214Z"
    },
    {
      "performance": 34,
      "accessibility": 100,
      "bestPractices": 56,
      "seo": 86,
      "timestamp": "2026-05-11T11:14:59.795Z"
    }
  ]
}