{
  "url": "https://redis.io/insight/",
  "runs": 3,
  "performance": 29,
  "accessibility": 100,
  "bestPractices": 74,
  "seo": 100,
  "timestamp": "2025-08-25T08:44:24.962Z",
  "rawResults": [
    {
      "performance": 29,
      "accessibility": 100,
      "bestPractices": 74,
      "seo": 100,
      "timestamp": "2025-08-25T08:42:10.498Z"
    },
    {
      "performance": 29,
      "accessibility": 100,
      "bestPractices": 74,
      "seo": 100,
      "timestamp": "2025-08-25T08:43:17.734Z"
    },
    {
      "performance": 29,
      "accessibility": 100,
      "bestPractices": 74,
      "seo": 100,
      "timestamp": "2025-08-25T08:44:24.962Z"
    }
  ]
}