{
  "url": "https://redis.io/meeting/",
  "runs": 3,
  "performance": 19,
  "accessibility": 100,
  "bestPractices": 56,
  "seo": 100,
  "timestamp": "2026-04-01T09:11:04.067Z",
  "rawResults": [
    {
      "performance": 15,
      "accessibility": 100,
      "bestPractices": 56,
      "seo": 100,
      "timestamp": "2026-04-01T09:08:34.812Z"
    },
    {
      "performance": 15,
      "accessibility": 100,
      "bestPractices": 56,
      "seo": 100,
      "timestamp": "2026-04-01T09:09:49.595Z"
    },
    {
      "performance": 27,
      "accessibility": 100,
      "bestPractices": 56,
      "seo": 100,
      "timestamp": "2026-04-01T09:11:04.067Z"
    }
  ]
}