{
  "url": "https://redis.io/meeting/",
  "runs": 3,
  "performance": 7,
  "accessibility": 100,
  "bestPractices": 56,
  "seo": 93,
  "timestamp": "2026-03-25T08:58:26.614Z",
  "rawResults": [
    {
      "performance": 7,
      "accessibility": 100,
      "bestPractices": 56,
      "seo": 93,
      "timestamp": "2026-03-25T08:55:50.975Z"
    },
    {
      "performance": 7,
      "accessibility": 100,
      "bestPractices": 56,
      "seo": 93,
      "timestamp": "2026-03-25T08:57:08.848Z"
    },
    {
      "performance": 7,
      "accessibility": 100,
      "bestPractices": 56,
      "seo": 93,
      "timestamp": "2026-03-25T08:58:26.614Z"
    }
  ]
}