{
  "url": "https://redis.io/pricing/",
  "runs": 3,
  "performance": 28,
  "accessibility": 96,
  "bestPractices": 74,
  "seo": 100,
  "timestamp": "2025-09-27T08:52:23.504Z",
  "rawResults": [
    {
      "performance": 28,
      "accessibility": 96,
      "bestPractices": 74,
      "seo": 100,
      "timestamp": "2025-09-27T08:50:10.425Z"
    },
    {
      "performance": 28,
      "accessibility": 96,
      "bestPractices": 74,
      "seo": 100,
      "timestamp": "2025-09-27T08:51:16.517Z"
    },
    {
      "performance": 28,
      "accessibility": 96,
      "bestPractices": 74,
      "seo": 100,
      "timestamp": "2025-09-27T08:52:23.504Z"
    }
  ]
}