{
  "url": "https://redis.io/software/",
  "runs": 3,
  "performance": 28,
  "accessibility": 100,
  "bestPractices": 74,
  "seo": 93,
  "timestamp": "2025-08-09T08:38:13.313Z",
  "rawResults": [
    {
      "performance": 27,
      "accessibility": 100,
      "bestPractices": 74,
      "seo": 93,
      "timestamp": "2025-08-09T08:35:54.944Z"
    },
    {
      "performance": 28,
      "accessibility": 100,
      "bestPractices": 74,
      "seo": 93,
      "timestamp": "2025-08-09T08:37:04.053Z"
    },
    {
      "performance": 28,
      "accessibility": 100,
      "bestPractices": 74,
      "seo": 93,
      "timestamp": "2025-08-09T08:38:13.313Z"
    }
  ]
}