{
  "url": "https://redis.io/software/",
  "runs": 3,
  "performance": 26,
  "accessibility": 100,
  "bestPractices": 56,
  "seo": 93,
  "timestamp": "2026-01-25T08:42:38.867Z",
  "rawResults": [
    {
      "performance": 27,
      "accessibility": 100,
      "bestPractices": 56,
      "seo": 93,
      "timestamp": "2026-01-25T08:40:12.298Z"
    },
    {
      "performance": 26,
      "accessibility": 100,
      "bestPractices": 56,
      "seo": 93,
      "timestamp": "2026-01-25T08:41:24.909Z"
    },
    {
      "performance": 26,
      "accessibility": 100,
      "bestPractices": 56,
      "seo": 93,
      "timestamp": "2026-01-25T08:42:38.867Z"
    }
  ]
}