{
  "url": "https://redis.io/resources/",
  "runs": 3,
  "performance": 29,
  "accessibility": 100,
  "bestPractices": 74,
  "seo": 100,
  "timestamp": "2025-09-17T08:52:21.963Z",
  "rawResults": [
    {
      "performance": 29,
      "accessibility": 100,
      "bestPractices": 74,
      "seo": 100,
      "timestamp": "2025-09-17T08:50:04.419Z"
    },
    {
      "performance": 29,
      "accessibility": 100,
      "bestPractices": 74,
      "seo": 100,
      "timestamp": "2025-09-17T08:51:13.212Z"
    },
    {
      "performance": 29,
      "accessibility": 100,
      "bestPractices": 74,
      "seo": 100,
      "timestamp": "2025-09-17T08:52:21.963Z"
    }
  ]
}