{
  "url": "https://redis.io/resources/",
  "runs": 3,
  "performance": 29,
  "accessibility": 92,
  "bestPractices": 74,
  "seo": 100,
  "timestamp": "2025-10-30T08:52:49.558Z",
  "rawResults": [
    {
      "performance": 29,
      "accessibility": 92,
      "bestPractices": 74,
      "seo": 100,
      "timestamp": "2025-10-30T08:50:33.751Z"
    },
    {
      "performance": 29,
      "accessibility": 92,
      "bestPractices": 74,
      "seo": 100,
      "timestamp": "2025-10-30T08:51:41.556Z"
    },
    {
      "performance": 29,
      "accessibility": 92,
      "bestPractices": 74,
      "seo": 100,
      "timestamp": "2025-10-30T08:52:49.558Z"
    }
  ]
}