{
  "url": "https://redis.io/software/",
  "runs": 3,
  "performance": 32,
  "accessibility": 100,
  "bestPractices": 74,
  "seo": 93,
  "timestamp": "2025-09-01T08:40:55.280Z",
  "rawResults": [
    {
      "performance": 42,
      "accessibility": 100,
      "bestPractices": 74,
      "seo": 93,
      "timestamp": "2025-09-01T08:38:37.580Z"
    },
    {
      "performance": 27,
      "accessibility": 100,
      "bestPractices": 74,
      "seo": 93,
      "timestamp": "2025-09-01T08:39:46.494Z"
    },
    {
      "performance": 27,
      "accessibility": 100,
      "bestPractices": 74,
      "seo": 93,
      "timestamp": "2025-09-01T08:40:55.280Z"
    }
  ]
}