{
  "url": "https://redis.io/try-free/",
  "runs": 3,
  "performance": 47,
  "accessibility": 100,
  "bestPractices": 74,
  "seo": 100,
  "timestamp": "2025-11-05T08:30:28.479Z",
  "rawResults": [
    {
      "performance": 48,
      "accessibility": 100,
      "bestPractices": 74,
      "seo": 100,
      "timestamp": "2025-11-05T08:28:27.144Z"
    },
    {
      "performance": 46,
      "accessibility": 100,
      "bestPractices": 74,
      "seo": 100,
      "timestamp": "2025-11-05T08:29:27.710Z"
    },
    {
      "performance": 46,
      "accessibility": 100,
      "bestPractices": 74,
      "seo": 100,
      "timestamp": "2025-11-05T08:30:28.479Z"
    }
  ]
}