{
  "url": "https://redis.io/resources/",
  "runs": 3,
  "performance": 34,
  "accessibility": 88,
  "bestPractices": 78,
  "seo": 86,
  "timestamp": "2025-08-08T08:55:37.749Z",
  "rawResults": [
    {
      "performance": 34,
      "accessibility": 88,
      "bestPractices": 78,
      "seo": 86,
      "timestamp": "2025-08-08T08:53:24.677Z"
    },
    {
      "performance": 34,
      "accessibility": 88,
      "bestPractices": 78,
      "seo": 86,
      "timestamp": "2025-08-08T08:54:31.279Z"
    },
    {
      "performance": 34,
      "accessibility": 88,
      "bestPractices": 78,
      "seo": 86,
      "timestamp": "2025-08-08T08:55:37.749Z"
    }
  ]
}