{
  "url": "https://redis.io/",
  "runs": 3,
  "performance": 26,
  "accessibility": 98,
  "bestPractices": 56,
  "seo": 93,
  "timestamp": "2026-02-27T08:41:13.606Z",
  "rawResults": [
    {
      "performance": 26,
      "accessibility": 98,
      "bestPractices": 56,
      "seo": 93,
      "timestamp": "2026-02-27T08:38:30.373Z"
    },
    {
      "performance": 26,
      "accessibility": 98,
      "bestPractices": 56,
      "seo": 93,
      "timestamp": "2026-02-27T08:39:52.132Z"
    },
    {
      "performance": 26,
      "accessibility": 98,
      "bestPractices": 56,
      "seo": 93,
      "timestamp": "2026-02-27T08:41:13.606Z"
    }
  ]
}