{
  "url": "https://redis.io/try-free/",
  "runs": 3,
  "performance": 48,
  "accessibility": 100,
  "bestPractices": 52,
  "seo": 100,
  "timestamp": "2026-01-01T08:33:00.591Z",
  "rawResults": [
    {
      "performance": 48,
      "accessibility": 100,
      "bestPractices": 52,
      "seo": 100,
      "timestamp": "2026-01-01T08:30:56.788Z"
    },
    {
      "performance": 47,
      "accessibility": 100,
      "bestPractices": 52,
      "seo": 100,
      "timestamp": "2026-01-01T08:31:58.534Z"
    },
    {
      "performance": 49,
      "accessibility": 100,
      "bestPractices": 52,
      "seo": 100,
      "timestamp": "2026-01-01T08:33:00.591Z"
    }
  ]
}