{
  "url": "https://redis.io/pricing/",
  "runs": 3,
  "performance": 28,
  "accessibility": 96,
  "bestPractices": 52,
  "seo": 100,
  "timestamp": "2025-12-18T09:02:55.028Z",
  "rawResults": [
    {
      "performance": 28,
      "accessibility": 96,
      "bestPractices": 52,
      "seo": 100,
      "timestamp": "2025-12-18T09:00:33.778Z"
    },
    {
      "performance": 28,
      "accessibility": 96,
      "bestPractices": 52,
      "seo": 100,
      "timestamp": "2025-12-18T09:01:44.617Z"
    },
    {
      "performance": 28,
      "accessibility": 96,
      "bestPractices": 52,
      "seo": 100,
      "timestamp": "2025-12-18T09:02:55.028Z"
    }
  ]
}