{
  "url": "https://redis.io/insight/",
  "runs": 3,
  "performance": 35,
  "accessibility": 100,
  "bestPractices": 56,
  "seo": 100,
  "timestamp": "2026-04-19T09:12:07.982Z",
  "rawResults": [
    {
      "performance": 35,
      "accessibility": 100,
      "bestPractices": 56,
      "seo": 100,
      "timestamp": "2026-04-19T09:09:44.115Z"
    },
    {
      "performance": 36,
      "accessibility": 100,
      "bestPractices": 56,
      "seo": 100,
      "timestamp": "2026-04-19T09:10:56.002Z"
    },
    {
      "performance": 35,
      "accessibility": 100,
      "bestPractices": 56,
      "seo": 100,
      "timestamp": "2026-04-19T09:12:07.982Z"
    }
  ]
}