{
  "url": "https://redis.io/cloud/",
  "runs": 3,
  "performance": 35,
  "accessibility": 100,
  "bestPractices": 74,
  "seo": 100,
  "timestamp": "2025-10-13T08:38:30.149Z",
  "rawResults": [
    {
      "performance": 28,
      "accessibility": 100,
      "bestPractices": 74,
      "seo": 100,
      "timestamp": "2025-10-13T08:36:14.675Z"
    },
    {
      "performance": 41,
      "accessibility": 100,
      "bestPractices": 74,
      "seo": 100,
      "timestamp": "2025-10-13T08:37:22.237Z"
    },
    {
      "performance": 37,
      "accessibility": 100,
      "bestPractices": 74,
      "seo": 100,
      "timestamp": "2025-10-13T08:38:30.149Z"
    }
  ]
}