{
  "url": "https://redis.io/resources/",
  "runs": 3,
  "performance": 27,
  "accessibility": 96,
  "bestPractices": 52,
  "seo": 93,
  "timestamp": "2026-01-13T09:00:25.062Z",
  "rawResults": [
    {
      "performance": 27,
      "accessibility": 96,
      "bestPractices": 52,
      "seo": 93,
      "timestamp": "2026-01-13T08:57:53.467Z"
    },
    {
      "performance": 26,
      "accessibility": 96,
      "bestPractices": 52,
      "seo": 93,
      "timestamp": "2026-01-13T08:59:09.182Z"
    },
    {
      "performance": 27,
      "accessibility": 96,
      "bestPractices": 52,
      "seo": 93,
      "timestamp": "2026-01-13T09:00:25.062Z"
    }
  ]
}