{
  "url": "https://redis.io/cloud/",
  "runs": 3,
  "performance": 28,
  "accessibility": 100,
  "bestPractices": 52,
  "seo": 100,
  "timestamp": "2025-12-22T08:41:34.045Z",
  "rawResults": [
    {
      "performance": 28,
      "accessibility": 100,
      "bestPractices": 52,
      "seo": 100,
      "timestamp": "2025-12-22T08:39:11.199Z"
    },
    {
      "performance": 28,
      "accessibility": 100,
      "bestPractices": 52,
      "seo": 100,
      "timestamp": "2025-12-22T08:40:22.597Z"
    },
    {
      "performance": 28,
      "accessibility": 100,
      "bestPractices": 52,
      "seo": 100,
      "timestamp": "2025-12-22T08:41:34.045Z"
    }
  ]
}