{
  "url": "https://redis.io/downloads/",
  "runs": 3,
  "performance": 27,
  "accessibility": 89,
  "bestPractices": 52,
  "seo": 100,
  "timestamp": "2026-01-07T08:51:57.724Z",
  "rawResults": [
    {
      "performance": 27,
      "accessibility": 89,
      "bestPractices": 52,
      "seo": 100,
      "timestamp": "2026-01-07T08:49:28.078Z"
    },
    {
      "performance": 26,
      "accessibility": 89,
      "bestPractices": 52,
      "seo": 100,
      "timestamp": "2026-01-07T08:50:40.505Z"
    },
    {
      "performance": 27,
      "accessibility": 89,
      "bestPractices": 52,
      "seo": 100,
      "timestamp": "2026-01-07T08:51:57.724Z"
    }
  ]
}