{
  "url": "https://redis.io/meeting/",
  "runs": 3,
  "performance": 28,
  "accessibility": 100,
  "bestPractices": 56,
  "seo": 100,
  "timestamp": "2026-04-15T09:26:19.869Z",
  "rawResults": [
    {
      "performance": 36,
      "accessibility": 100,
      "bestPractices": 56,
      "seo": 100,
      "timestamp": "2026-04-15T09:23:49.008Z"
    },
    {
      "performance": 31,
      "accessibility": 100,
      "bestPractices": 56,
      "seo": 100,
      "timestamp": "2026-04-15T09:25:04.370Z"
    },
    {
      "performance": 17,
      "accessibility": 100,
      "bestPractices": 56,
      "seo": 100,
      "timestamp": "2026-04-15T09:26:19.869Z"
    }
  ]
}