{
  "url": "https://redis.io/meeting/",
  "runs": 3,
  "performance": 24,
  "accessibility": 100,
  "bestPractices": 74,
  "seo": 100,
  "timestamp": "2025-11-27T08:35:09.323Z",
  "rawResults": [
    {
      "performance": 27,
      "accessibility": 100,
      "bestPractices": 74,
      "seo": 100,
      "timestamp": "2025-11-27T08:32:41.620Z"
    },
    {
      "performance": 22,
      "accessibility": 100,
      "bestPractices": 74,
      "seo": 100,
      "timestamp": "2025-11-27T08:33:53.018Z"
    },
    {
      "performance": 23,
      "accessibility": 100,
      "bestPractices": 74,
      "seo": 100,
      "timestamp": "2025-11-27T08:35:09.323Z"
    }
  ]
}