{
  "url": "https://redis.io/try-free/",
  "runs": 3,
  "performance": 43,
  "accessibility": 100,
  "bestPractices": 56,
  "seo": 100,
  "timestamp": "2026-03-31T09:02:01.239Z",
  "rawResults": [
    {
      "performance": 40,
      "accessibility": 100,
      "bestPractices": 56,
      "seo": 100,
      "timestamp": "2026-03-31T08:59:57.995Z"
    },
    {
      "performance": 41,
      "accessibility": 100,
      "bestPractices": 56,
      "seo": 100,
      "timestamp": "2026-03-31T09:00:59.629Z"
    },
    {
      "performance": 47,
      "accessibility": 100,
      "bestPractices": 56,
      "seo": 100,
      "timestamp": "2026-03-31T09:02:01.239Z"
    }
  ]
}